dls_dodal-1.69.0.dist-info/licenses/LICENSE
dodal/__init__.py
dodal/__main__.py
dodal/_version.py
dodal/cli.py
dodal/device_manager.py
dodal/log.py
dodal/utils.py
dodal/beamline_specific_utils/__init__.py
dodal/beamline_specific_utils/i05_shared.py
dodal/beamlines/README.md
dodal/beamlines/__init__.py
dodal/beamlines/adsim.py
dodal/beamlines/aithre.py
dodal/beamlines/b01_1.py
dodal/beamlines/b07.py
dodal/beamlines/b07_1.py
dodal/beamlines/b16.py
dodal/beamlines/b18.py
dodal/beamlines/b21.py
dodal/beamlines/i02_1.py
dodal/beamlines/i02_2.py
dodal/beamlines/i03.py
dodal/beamlines/i03_supervisor.py
dodal/beamlines/i04.py
dodal/beamlines/i05.py
dodal/beamlines/i05_1.py
dodal/beamlines/i06.py
dodal/beamlines/i06_1.py
dodal/beamlines/i07.py
dodal/beamlines/i09.py
dodal/beamlines/i09_1.py
dodal/beamlines/i09_2.py
dodal/beamlines/i10.py
dodal/beamlines/i10_1.py
dodal/beamlines/i10_optics.py
dodal/beamlines/i11.py
dodal/beamlines/i13_1.py
dodal/beamlines/i15.py
dodal/beamlines/i15_1.py
dodal/beamlines/i16.py
dodal/beamlines/i17.py
dodal/beamlines/i18.py
dodal/beamlines/i19_1.py
dodal/beamlines/i19_2.py
dodal/beamlines/i19_optics.py
dodal/beamlines/i20_1.py
dodal/beamlines/i21.py
dodal/beamlines/i22.py
dodal/beamlines/i23.py
dodal/beamlines/i24.py
dodal/beamlines/k07.py
dodal/beamlines/k11.py
dodal/beamlines/p38.py
dodal/beamlines/p45.py
dodal/beamlines/p60.py
dodal/beamlines/p99.py
dodal/beamlines/training_rig.py
dodal/common/__init__.py
dodal/common/coordination.py
dodal/common/crystal_metadata.py
dodal/common/data_util.py
dodal/common/device_utils.py
dodal/common/enums.py
dodal/common/maths.py
dodal/common/types.py
dodal/common/udc_directory_provider.py
dodal/common/visit.py
dodal/common/watcher_utils.py
dodal/common/beamlines/__init__.py
dodal/common/beamlines/beamline_parameters.py
dodal/common/beamlines/beamline_utils.py
dodal/common/beamlines/commissioning_mode.py
dodal/common/beamlines/device_helpers.py
dodal/devices/__init__.py
dodal/devices/aperture.py
dodal/devices/aperturescatterguard.py
dls_dodal-1.69.0.dist-info/METADATA
dls_dodal-1.69.0.dist-info/WHEEL
dls_dodal-1.69.0.dist-info/entry_points.txt
dls_dodal-1.69.0.dist-info/top_level.txt
dls_dodal-1.69.0.dist-info/RECORD
