Metadata-Version: 2.4
Name: dls-dodal
Version: 1.69.0
Summary: Ophyd devices and other utils that could be used across DLS beamlines
Author-email: Dominic Oram <dominic.oram@diamond.ac.uk>, Joseph Ware <joseph.ware@diamond.ac.uk>, Oliver Silvester <Oliver.Silvester@diamond.ac.uk>, Noemi Frisina <noemi.frisina@diamond.ac.uk>
License:                                  Apache License
Project-URL: GitHub, https://github.com/DiamondLightSource/dodal
Classifier: Development Status :: 3 - Alpha
Classifier: License :: OSI Approved :: Apache Software License
Classifier: Programming Language :: Python :: 3.11
Classifier: Programming Language :: Python :: 3.12
Requires-Python: >=3.11
License-File: LICENSE
Requires-Dist: click
Requires-Dist: ophyd
Requires-Dist: ophyd-async[ca,pva]>=v0.14.0
Requires-Dist: bluesky>=1.14.5
Requires-Dist: pyepics
Requires-Dist: pillow
Requires-Dist: zocalo>=1.0.0
Requires-Dist: requests
Requires-Dist: graypy
Requires-Dist: pydantic>=2.0
Requires-Dist: opencv-python-headless
Requires-Dist: numpy
Requires-Dist: aiofiles
Requires-Dist: aiohttp
Requires-Dist: redis
Requires-Dist: scanspec>=0.7.3
Requires-Dist: pyzmq==26.3.0
Requires-Dist: deepdiff
Requires-Dist: daq-config-server>=v1.0.0
Dynamic: license-file
